[
    {
        "statusCode": "0000",
        "statusMessage": "Successful",
        "originalTrxID": "8KO3056RN7",
        "refundTrxID": "8KO6056RNA",
        "transactionStatus": "Completed",
        "amount": "20",
        "currency": "BDT",
        "charge": "0.00",
        "completedTime": "2021-11-24T01:07:07:689 GMT+0600"
    },
    {
        "statusCode": "0000",
        "statusMessage": "Successful",
        "originalTrxID": "8KO8056RNC",
        "refundTrxID": "8KO0056RNE",
        "transactionStatus": "Completed",
        "amount": "15",
        "currency": "BDT",
        "charge": "0.00",
        "completedTime": "2021-11-24T01:09:36:990 GMT+0600"
    },
    {
        "statusCode": "0000",
        "statusMessage": "Successful",
        "originalTrxID": "8KO1056TKL",
        "refundTrxID": "8KO5056SY7",
        "transactionStatus": "Completed",
        "amount": "10",
        "currency": "BDT",
        "charge": "0.00",
        "completedTime": "2021-11-24T12:45:55:206 GMT+0600"
    },
    {
        "statusCode": "0000",
        "statusMessage": "Successful",
        "originalTrxID": "8KO9056TM7",
        "refundTrxID": "8KO4056T36",
        "transactionStatus": "Completed",
        "amount": "10",
        "currency": "BDT",
        "charge": "0.00",
        "completedTime": "2021-11-24T13:50:42:373 GMT+0600"
    }
]